[
    {
        "username": "ResoluteBot",
        "release_time": {
            "year": 2022,
            "month": 3,
            "day": 20,
            "hour": 13,
            "minute": 32
        },
        "multiplier": 1
    },
    {
        "username": "chesssevigcom",
        "release_time": {
            "year": 2022,
            "month": 3,
            "day": 20,
            "hour": 13,
            "minute": 54
        },
        "multiplier": 1
    },
    {
        "username": "Karpov_bot",
        "release_time": {
            "year": 2022,
            "month": 3,
            "day": 21,
            "hour": 0,
            "minute": 53
        },
        "multiplier": 3
    },
    {
        "username": "Alehkine_cat",
        "release_time": {
            "year": 2022,
            "month": 3,
            "day": 15,
            "hour": 1,
            "minute": 10
        },
        "multiplier": 1
    },
    {
        "username": "Variants-Strong-Bot",
        "release_time": {
            "year": 2022,
            "month": 3,
            "day": 21,
            "hour": 17,
            "minute": 34
        },
        "multiplier": 8
    },
    {
        "username": "DOCTAL",
        "release_time": {
            "year": 2022,
            "month": 3,
            "day": 20,
            "hour": 13,
            "minute": 21
        },
        "multiplier": 1
    },
    {
        "username": "Hathor-Engine",
        "release_time": {
            "year": 2022,
            "month": 3,
            "day": 21,
            "hour": 21,
            "minute": 11
        },
        "multiplier": 9
    },
    {
        "username": "LegendofDragons",
        "release_time": {
            "year": 2022,
            "month": 3,
            "day": 18,
            "hour": 18,
            "minute": 6
        },
        "multiplier": 1
    },
    {
        "username": "WindowsR",
        "release_time": {
            "year": 2022,
            "month": 3,
            "day": 15,
            "hour": 16,
            "minute": 47
        },
        "multiplier": 1
    },
    {
        "username": "STANDARDSTOCKFISH",
        "release_time": {
            "year": 2022,
            "month": 3,
            "day": 21,
            "hour": 17,
            "minute": 10
        },
        "multiplier": 8
    },
    {
        "username": "YoBot_v2",
        "release_time": {
            "year": 2022,
            "month": 3,
            "day": 18,
            "hour": 18,
            "minute": 54
        },
        "multiplier": 1
    },
    {
        "username": "StableBassistPony",
        "release_time": {
            "year": 2022,
            "month": 3,
            "day": 20,
            "hour": 1,
            "minute": 30
        },
        "multiplier": 9
    },
    {
        "username": "TheEnisBotOfficial",
        "release_time": {
            "year": 2022,
            "month": 3,
            "day": 19,
            "hour": 9,
            "minute": 56
        },
        "multiplier": 5
    },
    {
        "username": "lord-bot",
        "release_time": {
            "year": 2022,
            "month": 3,
            "day": 18,
            "hour": 17,
            "minute": 44
        },
        "multiplier": 1
    },
    {
        "username": "STockfishdestroyBot",
        "release_time": {
            "year": 2022,
            "month": 3,
            "day": 20,
            "hour": 13,
            "minute": 58
        },
        "multiplier": 1
    },
    {
        "username": "NationalBot",
        "release_time": {
            "year": 2022,
            "month": 3,
            "day": 19,
            "hour": 23,
            "minute": 18
        },
        "multiplier": 8
    },
    {
        "username": "BlazikenBot2000",
        "release_time": {
            "year": 2022,
            "month": 3,
            "day": 20,
            "hour": 12,
            "minute": 57
        },
        "multiplier": 1
    },
    {
        "username": "ROBOT_RANDEER2007",
        "release_time": {
            "year": 2022,
            "month": 3,
            "day": 18,
            "hour": 18,
            "minute": 28
        },
        "multiplier": 1
    },
    {
        "username": "Li-Bot",
        "release_time": {
            "year": 2022,
            "month": 3,
            "day": 14,
            "hour": 10,
            "minute": 20
        },
        "multiplier": 1
    },
    {
        "username": "VariantsStockfish",
        "release_time": {
            "year": 2022,
            "month": 3,
            "day": 18,
            "hour": 16,
            "minute": 12
        },
        "multiplier": 1
    },
    {
        "username": "Lord-Chess-Bot",
        "release_time": {
            "year": 2022,
            "month": 3,
            "day": 14,
            "hour": 7,
            "minute": 22
        },
        "multiplier": 1
    },
    {
        "username": "Dragon_1906",
        "release_time": {
            "year": 2022,
            "month": 3,
            "day": 11,
            "hour": 15,
            "minute": 18
        },
        "multiplier": 2
    },
    {
        "username": "Strong_ehsan333",
        "release_time": {
            "year": 2022,
            "month": 3,
            "day": 15,
            "hour": 1,
            "minute": 50
        },
        "multiplier": 1
    },
    {
        "username": "ElexusChess",
        "release_time": {
            "year": 2022,
            "month": 3,
            "day": 15,
            "hour": 1,
            "minute": 7
        },
        "multiplier": 1
    },
    {
        "username": "Chrobot123chathu",
        "release_time": {
            "year": 2022,
            "month": 3,
            "day": 14,
            "hour": 7,
            "minute": 31
        },
        "multiplier": 1
    },
    {
        "username": "Satyakeswara_BOT",
        "release_time": {
            "year": 2022,
            "month": 3,
            "day": 15,
            "hour": 5,
            "minute": 33
        },
        "multiplier": 2
    },
    {
        "username": "Dean_Summer_Bot",
        "release_time": {
            "year": 2022,
            "month": 3,
            "day": 15,
            "hour": 15,
            "minute": 56
        },
        "multiplier": 1
    },
    {
        "username": "VariantTourneysBot",
        "release_time": {
            "year": 2022,
            "month": 3,
            "day": 11,
            "hour": 15,
            "minute": 18
        },
        "multiplier": 1
    },
    {
        "username": "lichapibot",
        "release_time": {
            "year": 2022,
            "month": 3,
            "day": 11,
            "hour": 15,
            "minute": 18
        },
        "multiplier": 1
    },
    {
        "username": "Dark_evil_bot",
        "release_time": {
            "year": 2022,
            "month": 3,
            "day": 15,
            "hour": 5,
            "minute": 48
        },
        "multiplier": 3
    },
    {
        "username": "SkyBlaster",
        "release_time": {
            "year": 2022,
            "month": 3,
            "day": 14,
            "hour": 6,
            "minute": 49
        },
        "multiplier": 1
    },
    {
        "username": "TeamChelsie",
        "release_time": {
            "year": 2022,
            "month": 3,
            "day": 11,
            "hour": 15,
            "minute": 18
        },
        "multiplier": 2
    },
    {
        "username": "WennDieSoldatBOT",
        "release_time": {
            "year": 2022,
            "month": 3,
            "day": 11,
            "hour": 15,
            "minute": 18
        },
        "multiplier": 2
    },
    {
        "username": "stockfish_Johan",
        "release_time": {
            "year": 2022,
            "month": 3,
            "day": 19,
            "hour": 6,
            "minute": 3
        },
        "multiplier": 4
    },
    {
        "username": "speedestbot",
        "release_time": {
            "year": 2022,
            "month": 3,
            "day": 14,
            "hour": 9,
            "minute": 2
        },
        "multiplier": 1
    },
    {
        "username": "kaluganthota",
        "release_time": {
            "year": 2022,
            "month": 3,
            "day": 14,
            "hour": 8,
            "minute": 29
        },
        "multiplier": 2
    },
    {
        "username": "Lila-Stockfish",
        "release_time": {
            "year": 2022,
            "month": 3,
            "day": 14,
            "hour": 6,
            "minute": 33
        },
        "multiplier": 1
    },
    {
        "username": "power_bot",
        "release_time": {
            "year": 2022,
            "month": 3,
            "day": 14,
            "hour": 10,
            "minute": 58
        },
        "multiplier": 3
    },
    {
        "username": "SkyAttacker",
        "release_time": {
            "year": 2022,
            "month": 3,
            "day": 15,
            "hour": 11,
            "minute": 6
        },
        "multiplier": 4
    },
    {
        "username": "land-bot",
        "release_time": {
            "year": 2022,
            "month": 3,
            "day": 14,
            "hour": 6,
            "minute": 39
        },
        "multiplier": 1
    },
    {
        "username": "LazyBot",
        "release_time": {
            "year": 2022,
            "month": 3,
            "day": 11,
            "hour": 15,
            "minute": 18
        },
        "multiplier": 2
    },
    {
        "username": "M07002",
        "release_time": {
            "year": 2022,
            "month": 3,
            "day": 13,
            "hour": 19,
            "minute": 52
        },
        "multiplier": 1
    },
    {
        "username": "Chesshelper1234",
        "release_time": {
            "year": 2022,
            "month": 3,
            "day": 11,
            "hour": 15,
            "minute": 18
        },
        "multiplier": 1
    },
    {
        "username": "Magnus-BOT",
        "release_time": {
            "year": 2022,
            "month": 3,
            "day": 11,
            "hour": 15,
            "minute": 18
        },
        "multiplier": 1
    },
    {
        "username": "Raised_Bot",
        "release_time": {
            "year": 2022,
            "month": 3,
            "day": 11,
            "hour": 15,
            "minute": 18
        },
        "multiplier": 1
    },
    {
        "username": "Nowinforyoukid",
        "release_time": {
            "year": 2022,
            "month": 3,
            "day": 12,
            "hour": 14,
            "minute": 51
        },
        "multiplier": 1
    },
    {
        "username": "StockfishPower",
        "release_time": {
            "year": 2022,
            "month": 3,
            "day": 15,
            "hour": 3,
            "minute": 14
        },
        "multiplier": 1
    },
    {
        "username": "beckapplebot",
        "release_time": {
            "year": 2022,
            "month": 3,
            "day": 14,
            "hour": 7,
            "minute": 45
        },
        "multiplier": 1
    },
    {
        "username": "Hyper-Bot11",
        "release_time": {
            "year": 2022,
            "month": 3,
            "day": 15,
            "hour": 16,
            "minute": 17
        },
        "multiplier": 1
    },
    {
        "username": "Pro-Python-BOT",
        "release_time": {
            "year": 2022,
            "month": 3,
            "day": 11,
            "hour": 15,
            "minute": 18
        },
        "multiplier": 1
    },
    {
        "username": "PressAltPlusF4",
        "release_time": {
            "year": 2022,
            "month": 3,
            "day": 14,
            "hour": 6,
            "minute": 38
        },
        "multiplier": 1
    },
    {
        "username": "Clash_Bot",
        "release_time": {
            "year": 2022,
            "month": 3,
            "day": 14,
            "hour": 6,
            "minute": 56
        },
        "multiplier": 1
    },
    {
        "username": "ToromBot",
        "release_time": {
            "year": 2022,
            "month": 3,
            "day": 15,
            "hour": 5,
            "minute": 27
        },
        "multiplier": 4
    },
    {
        "username": "chesshyperbot",
        "release_time": {
            "year": 2022,
            "month": 3,
            "day": 15,
            "hour": 15,
            "minute": 47
        },
        "multiplier": 1
    },
    {
        "username": "P40ToForget",
        "release_time": {
            "year": 2022,
            "month": 3,
            "day": 12,
            "hour": 15,
            "minute": 14
        },
        "multiplier": 1
    },
    {
        "username": "M07001",
        "release_time": {
            "year": 2022,
            "month": 3,
            "day": 13,
            "hour": 18,
            "minute": 35
        },
        "multiplier": 1
    },
    {
        "username": "caissa-x",
        "release_time": {
            "year": 2022,
            "month": 3,
            "day": 18,
            "hour": 22,
            "minute": 16
        },
        "multiplier": 2
    },
    {
        "username": "Palisade",
        "release_time": {
            "year": 2022,
            "month": 3,
            "day": 13,
            "hour": 16,
            "minute": 51
        },
        "multiplier": 2
    },
    {
        "username": "TestingStockfish",
        "release_time": {
            "year": 2022,
            "month": 3,
            "day": 15,
            "hour": 2,
            "minute": 56
        },
        "multiplier": 1
    },
    {
        "username": "AndScacs1",
        "release_time": {
            "year": 2022,
            "month": 3,
            "day": 13,
            "hour": 10,
            "minute": 14
        },
        "multiplier": 2
    },
    {
        "username": "JOKER_BOT",
        "release_time": {
            "year": 2022,
            "month": 3,
            "day": 14,
            "hour": 5,
            "minute": 42
        },
        "multiplier": 2
    },
    {
        "username": "ElPeonElectrico",
        "release_time": {
            "year": 2022,
            "month": 3,
            "day": 15,
            "hour": 9,
            "minute": 36
        },
        "multiplier": 4
    },
    {
        "username": "abhisun_bot",
        "release_time": {
            "year": 2022,
            "month": 3,
            "day": 16,
            "hour": 8,
            "minute": 23
        },
        "multiplier": 5
    },
    {
        "username": "WumpusDragonEngi",
        "release_time": {
            "year": 2022,
            "month": 3,
            "day": 13,
            "hour": 19,
            "minute": 16
        },
        "multiplier": 1
    },
    {
        "username": "XXIstCentury",
        "release_time": {
            "year": 2022,
            "month": 3,
            "day": 13,
            "hour": 20,
            "minute": 16
        },
        "multiplier": 1
    },
    {
        "username": "WalterUlbrichtRobot",
        "release_time": {
            "year": 2022,
            "month": 3,
            "day": 14,
            "hour": 10,
            "minute": 40
        },
        "multiplier": 3
    },
    {
        "username": "OfficalBot_1906",
        "release_time": {
            "year": 2022,
            "month": 3,
            "day": 15,
            "hour": 3,
            "minute": 5
        },
        "multiplier": 1
    },
    {
        "username": "Dranzer1",
        "release_time": {
            "year": 2022,
            "month": 3,
            "day": 15,
            "hour": 0,
            "minute": 57
        },
        "multiplier": 1
    },
    {
        "username": "tufile",
        "release_time": {
            "year": 2022,
            "month": 3,
            "day": 19,
            "hour": 9,
            "minute": 56
        },
        "multiplier": 5
    },
    {
        "username": "Resolved-Bot",
        "release_time": {
            "year": 2022,
            "month": 3,
            "day": 15,
            "hour": 16,
            "minute": 32
        },
        "multiplier": 1
    },
    {
        "username": "JPSBOT",
        "release_time": {
            "year": 2022,
            "month": 3,
            "day": 16,
            "hour": 0,
            "minute": 36
        },
        "multiplier": 3
    },
    {
        "username": "BRAINLEARN11_NNUE",
        "release_time": {
            "year": 2022,
            "month": 3,
            "day": 14,
            "hour": 8,
            "minute": 2
        },
        "multiplier": 2
    },
    {
        "username": "Major_Max_Bot",
        "release_time": {
            "year": 2022,
            "month": 3,
            "day": 15,
            "hour": 2,
            "minute": 54
        },
        "multiplier": 1
    },
    {
        "username": "AnUtterlyKarBot",
        "release_time": {
            "year": 2022,
            "month": 3,
            "day": 14,
            "hour": 6,
            "minute": 46
        },
        "multiplier": 1
    },
    {
        "username": "faith_bot",
        "release_time": {
            "year": 2022,
            "month": 3,
            "day": 14,
            "hour": 5,
            "minute": 47
        },
        "multiplier": 1
    },
    {
        "username": "The-Fastest-Bot",
        "release_time": {
            "year": 2022,
            "month": 3,
            "day": 14,
            "hour": 8,
            "minute": 29
        },
        "multiplier": 2
    },
    {
        "username": "Dr-energy",
        "release_time": {
            "year": 2022,
            "month": 3,
            "day": 14,
            "hour": 8,
            "minute": 29
        },
        "multiplier": 2
    },
    {
        "username": "NormalBlitzBulletBot",
        "release_time": {
            "year": 2022,
            "month": 3,
            "day": 14,
            "hour": 6,
            "minute": 48
        },
        "multiplier": 2
    },
    {
        "username": "TheGlassChess",
        "release_time": {
            "year": 2022,
            "month": 3,
            "day": 19,
            "hour": 2,
            "minute": 2
        },
        "multiplier": 3
    },
    {
        "username": "McB0t",
        "release_time": {
            "year": 2022,
            "month": 3,
            "day": 14,
            "hour": 8,
            "minute": 14
        },
        "multiplier": 1
    },
    {
        "username": "Dark_Lightning",
        "release_time": {
            "year": 2022,
            "month": 3,
            "day": 15,
            "hour": 3,
            "minute": 9
        },
        "multiplier": 2
    },
    {
        "username": "Sharkbot",
        "release_time": {
            "year": 2022,
            "month": 3,
            "day": 15,
            "hour": 5,
            "minute": 31
        },
        "multiplier": 2
    },
    {
        "username": "Chesu11",
        "release_time": {
            "year": 2022,
            "month": 3,
            "day": 15,
            "hour": 5,
            "minute": 33
        },
        "multiplier": 2
    },
    {
        "username": "Brabemachess-BOT",
        "release_time": {
            "year": 2022,
            "month": 3,
            "day": 15,
            "hour": 20,
            "minute": 43
        },
        "multiplier": 2
    },
    {
        "username": "Hyper_BOT88",
        "release_time": {
            "year": 2022,
            "month": 3,
            "day": 21,
            "hour": 20,
            "minute": 5
        },
        "multiplier": 3
    },
    {
        "username": "HyperBOT_Debopam",
        "release_time": {
            "year": 2022,
            "month": 3,
            "day": 21,
            "hour": 20,
            "minute": 5
        },
        "multiplier": 3
    },
    {
        "username": "jangine",
        "release_time": {
            "year": 2022,
            "month": 3,
            "day": 21,
            "hour": 20,
            "minute": 11
        },
        "multiplier": 3
    },
    {
        "username": "Kenjali_bot",
        "release_time": {
            "year": 2022,
            "month": 3,
            "day": 21,
            "hour": 15,
            "minute": 16
        },
        "multiplier": 3
    },
    {
        "username": "Luci-fStockfish",
        "release_time": {
            "year": 2022,
            "month": 3,
            "day": 21,
            "hour": 20,
            "minute": 12
        },
        "multiplier": 3
    },
    {
        "username": "Mega-BOT",
        "release_time": {
            "year": 2022,
            "month": 3,
            "day": 21,
            "hour": 20,
            "minute": 12
        },
        "multiplier": 3
    },
    {
        "username": "nyiblaok",
        "release_time": {
            "year": 2022,
            "month": 3,
            "day": 18,
            "hour": 21,
            "minute": 56
        },
        "multiplier": 2
    },
    {
        "username": "Original_Bot",
        "release_time": {
            "year": 2022,
            "month": 3,
            "day": 18,
            "hour": 18,
            "minute": 40
        },
        "multiplier": 2
    },
    {
        "username": "Play-VladimirChess",
        "release_time": {
            "year": 2022,
            "month": 3,
            "day": 18,
            "hour": 21,
            "minute": 58
        },
        "multiplier": 2
    },
    {
        "username": "shiro_botv3",
        "release_time": {
            "year": 2022,
            "month": 3,
            "day": 18,
            "hour": 21,
            "minute": 58
        },
        "multiplier": 2
    },
    {
        "username": "SuperChessEngine",
        "release_time": {
            "year": 2022,
            "month": 3,
            "day": 18,
            "hour": 21,
            "minute": 58
        },
        "multiplier": 2
    },
    {
        "username": "NimsiluBot",
        "release_time": {
            "year": 2022,
            "month": 3,
            "day": 18,
            "hour": 17,
            "minute": 29
        },
        "multiplier": 1
    },
    {
        "username": "Stobot",
        "release_time": {
            "year": 2022,
            "month": 3,
            "day": 20,
            "hour": 14,
            "minute": 53
        },
        "multiplier": 1
    },
    {
        "username": "IndianMagnet",
        "release_time": {
            "year": 2022,
            "month": 3,
            "day": 21,
            "hour": 10,
            "minute": 51
        },
        "multiplier": 1
    }
]